LICENSE
README.md
setup.py
tiny_dlna/__init__.py
tiny_dlna/tiny_cli.py
tiny_dlna/tiny_render.py
tiny_dlna/tiny_ssdp.py
tiny_dlna/tiny_xmls.py
tiny_dlna/version
tiny_dlna.egg-info/PKG-INFO
tiny_dlna.egg-info/SOURCES.txt
tiny_dlna.egg-info/dependency_links.txt
tiny_dlna.egg-info/entry_points.txt
tiny_dlna.egg-info/requires.txt
tiny_dlna.egg-info/top_level.txt