Metadata-Version: 2.4
Name: tiny_dlna
Version: 0.12.1
Summary: a tiny DLNA sender & receiver
Home-page: https://github.com/mitnk/tiny-dlna
Author: mitnk
License: MIT
Keywords: dlna
License-File: LICENSE
Requires-Dist: flask>=3.0.0
Requires-Dist: psutil>=6.0.0
Dynamic: author
Dynamic: description
Dynamic: home-page
Dynamic: keywords
Dynamic: license
Dynamic: license-file
Dynamic: requires-dist
Dynamic: summary
